mashdb/__init__.py
mashdb/core.py
mashdb/bin/MashDB
mashdb-0.1.1.dist-info/licenses/LICENSE
mashdb-0.1.1.dist-info/METADATA
mashdb-0.1.1.dist-info/WHEEL
mashdb-0.1.1.dist-info/entry_points.txt
mashdb-0.1.1.dist-info/top_level.txt
mashdb-0.1.1.dist-info/RECORD
